sage_libs/__init__.py
sage_libs/sage_safety/__init__.py
sage_libs/sage_safety/_register.py
sage_libs/sage_safety/_version.py
sage_libs/sage_safety/detectors/__init__.py
sage_libs/sage_safety/detectors/keyword_jailbreak.py
sage_libs/sage_safety/detectors/simple_toxicity.py
sage_libs/sage_safety/guardrails/__init__.py
sage_libs/sage_safety/guardrails/pattern_guardrail.py
sage_libs/sage_safety/guardrails/rule_based_guardrail.py
isage_safety-0.1.0.0.dist-info/METADATA
isage_safety-0.1.0.0.dist-info/WHEEL
isage_safety-0.1.0.0.dist-info/top_level.txt
isage_safety-0.1.0.0.dist-info/RECORD
