Metadata-Version: 2.4
Name: isage-safety
Version: 0.1.0.0
Summary: SAGE Safety Framework - Safety guardrails and detectors for AI systems
Author-email: IntelliStream Team <shuhao_zhang@hust.edu.cn>
License-Expression: MIT
Project-URL: Homepage, https://github.com/intellistream/sage-safety
Project-URL: Repository, https://github.com/intellistream/sage-safety
Keywords: safety,guardrails,detector,content-moderation,LLM,AI
Requires-Python: >=3.10
Requires-Dist: pydantic>=2.0.0
Requires-Dist: typing-extensions>=4.0.0
Provides-Extra: dev
Requires-Dist: pytest>=7.0.0; extra == "dev"
Requires-Dist: pytest-asyncio>=0.21.0; extra == "dev"
Requires-Dist: ruff>=0.4.0; extra == "dev"
